Workbook

Sheet Dashboard
A1: SMALL BUSINESS COMMAND CENTER PREMIUM
A2: Excel-based business management toolkit
A3: Use the other sheets to record activity; summaries update from the sample formulas. Replace demo rows with your own data.
A4: Metric | B4: Value
A5: Sales total | B5: =SUM(Sales!E2:E501)
A6: Expenses total | B6: =SUM(Expenses!D2:D501)
A7: Estimated net | B7: =B5-B6
A8: Customers | B8: =COUNTA(Customers!A2:A501)
A9: Products | B9: =COUNTA(Products!A2:A501)
A10: Low-stock products | B10: =SUMPRODUCT(--(Products!D2:D501<=Products!E2:E501))
A12: Included modules | B12: Purpose
A13: Sales | B13: Record each sale and customer
A14: Expenses | B14: Track business costs by category
A15: Customers | B15: Customer contact list
A16: Products | B16: Inventory and reorder threshold
A17: Invoices | B17: Invoice amount, due date and payment status
A18: Tasks & KPI | B18: Tasks, goals, priorities and due dates
A19: Services | B19: Reusable service pricing, costs and document checklist
A20: Monthly Summary | B20: Monthly sales, costs, net and trend chart
A21: Buyer Guide | B21: Setup steps, assumptions and limitations

Sheet Sales
A1: Date | B1: Sale ID | C1: Customer | D1: Description | E1: Amount (INR) | F1: Payment Status | G1: Notes
A2: 46304 | B2: S-1001 | C2: Demo customer | D2: Website setup | E2: 12500 | F2: Paid | G2: Sample row — replace
A3: 46304 | B3: S-1002 | C3: Demo customer | D3: Monthly support | E3: 2500 | F3: Pending | G3: Sample row — replace

Sheet Expenses
A1: Date | B1: Category | C1: Description | D1: Amount (INR) | E1: Payment method | F1: Notes
A2: 46304 | B2: Software | C2: Design software | D2: 1200 | E2: Card | F2: Sample row — replace
A3: 46304 | B3: Internet | C3: Business internet | D3: 800 | E3: UPI | F3: Sample row — replace

Sheet Customers
A1: Customer Name | B1: Company | C1: Phone | D1: Email | E1: Address | F1: Notes
A2: Demo customer | B2: Example Studio | C2: +91 90000 00000 | D2: demo@example.com | F2: Sample data only

Sheet Products
A1: Product Name | B1: SKU | C1: Category | D1: Current Stock | E1: Reorder Level | F1: Unit Cost (INR) | G1: Selling Price (INR) | H1: Stock Cost Value
A2: Sample notebook | B2: NB-001 | C2: Stationery | D2: 8 | E2: 10 | F2: 45 | G2: 80 | H2: =D2*F2
A3: Sample pen | B3: PN-001 | C3: Stationery | D3: 45 | E3: 15 | F3: 8 | G3: 15 | H3: =D3*F3

Sheet Invoices
A1: Invoice No. | B1: Date | C1: Customer | D1: Description | E1: Subtotal (INR) | F1: Tax Rate % | G1: Tax (INR) | H1: Total (INR) | I1: Due Date | J1: Payment Status
A2: INV-1001 | B2: 46304 | C2: Demo customer | D2: Website setup | E2: 12500 | F2: 0 | G2: =E2*F2/100 | H2: =E2+G2 | I2: 46311 | J2: Paid

Sheet Tasks & KPI
A1: Task / Goal | B1: Owner | C1: Priority | D1: Due Date | E1: Status | F1: Target / KPI | G1: Actual | H1: Notes
A2: Send monthly report | B2: Owner | C2: High | D2: 46307 | E2: In progress | F2: 1 report | G2: 0 | H2: Sample task

Sheet Services
A1: Service Name | B1: Type | C1: Customer Charge (INR) | D1: Direct Cost (INR) | E1: Other Costs (INR) | F1: Estimated Profit (INR) | G1: Processing Time | H1: Required Documents Checklist
A2: Online form assistance | B2: Online service | C2: 500 | D2: 150 | E2: 30 | F2: =C2-D2-E2 | G2: 1 day | H2: Define and verify requirements yourself

Sheet Monthly Summary
A1: Month | B1: Sales (INR) | C1: Expenses (INR) | D1: Estimated Net (INR)
A2: Jan 2026 | B2: =SUMIFS(Sales!$E$2:$E$501,Sales!$A$2:$A$501,">="&DATE(2026,1,1),Sales!$A$2:$A$501,"<="&EOMONTH(DATE(2026,1,1),0)) | C2: =SUMIFS(Expenses!$D$2:$D$501,Expenses!$A$2:$A$501,">="&DATE(2026,1,1),Expenses!$A$2:$A$501,"<="&EOMONTH(DATE(2026,1,1),0)) | D2: =B2-C2
A3: Feb 2026 | B3: =SUMIFS(Sales!$E$2:$E$501,Sales!$A$2:$A$501,">="&DATE(2026,2,1),Sales!$A$2:$A$501,"<="&EOMONTH(DATE(2026,2,1),0)) | C3: =SUMIFS(Expenses!$D$2:$D$501,Expenses!$A$2:$A$501,">="&DATE(2026,2,1),Expenses!$A$2:$A$501,"<="&EOMONTH(DATE(2026,2,1),0)) | D3: =B3-C3
A4: Mar 2026 | B4: =SUMIFS(Sales!$E$2:$E$501,Sales!$A$2:$A$501,">="&DATE(2026,3,1),Sales!$A$2:$A$501,"<="&EOMONTH(DATE(2026,3,1),0)) | C4: =SUMIFS(Expenses!$D$2:$D$501,Expenses!$A$2:$A$501,">="&DATE(2026,3,1),Expenses!$A$2:$A$501,"<="&EOMONTH(DATE(2026,3,1),0)) | D4: =B4-C4
A5: Apr 2026 | B5: =SUMIFS(Sales!$E$2:$E$501,Sales!$A$2:$A$501,">="&DATE(2026,4,1),Sales!$A$2:$A$501,"<="&EOMONTH(DATE(2026,4,1),0)) | C5: =SUMIFS(Expenses!$D$2:$D$501,Expenses!$A$2:$A$501,">="&DATE(2026,4,1),Expenses!$A$2:$A$501,"<="&EOMONTH(DATE(2026,4,1),0)) | D5: =B5-C5
A6: May 2026 | B6: =SUMIFS(Sales!$E$2:$E$501,Sales!$A$2:$A$501,">="&DATE(2026,5,1),Sales!$A$2:$A$501,"<="&EOMONTH(DATE(2026,5,1),0)) | C6: =SUMIFS(Expenses!$D$2:$D$501,Expenses!$A$2:$A$501,">="&DATE(2026,5,1),Expenses!$A$2:$A$501,"<="&EOMONTH(DATE(2026,5,1),0)) | D6: =B6-C6
A7: Jun 2026 | B7: =SUMIFS(Sales!$E$2:$E$501,Sales!$A$2:$A$501,">="&DATE(2026,6,1),Sales!$A$2:$A$501,"<="&EOMONTH(DATE(2026,6,1),0)) | C7: =SUMIFS(Expenses!$D$2:$D$501,Expenses!$A$2:$A$501,">="&DATE(2026,6,1),Expenses!$A$2:$A$501,"<="&EOMONTH(DATE(2026,6,1),0)) | D7: =B7-C7
A8: Jul 2026 | B8: =SUMIFS(Sales!$E$2:$E$501,Sales!$A$2:$A$501,">="&DATE(2026,7,1),Sales!$A$2:$A$501,"<="&EOMONTH(DATE(2026,7,1),0)) | C8: =SUMIFS(Expenses!$D$2:$D$501,Expenses!$A$2:$A$501,">="&DATE(2026,7,1),Expenses!$A$2:$A$501,"<="&EOMONTH(DATE(2026,7,1),0)) | D8: =B8-C8
A9: Aug 2026 | B9: =SUMIFS(Sales!$E$2:$E$501,Sales!$A$2:$A$501,">="&DATE(2026,8,1),Sales!$A$2:$A$501,"<="&EOMONTH(DATE(2026,8,1),0)) | C9: =SUMIFS(Expenses!$D$2:$D$501,Expenses!$A$2:$A$501,">="&DATE(2026,8,1),Expenses!$A$2:$A$501,"<="&EOMONTH(DATE(2026,8,1),0)) | D9: =B9-C9
A10: Sep 2026 | B10: =SUMIFS(Sales!$E$2:$E$501,Sales!$A$2:$A$501,">="&DATE(2026,9,1),Sales!$A$2:$A$501,"<="&EOMONTH(DATE(2026,9,1),0)) | C10: =SUMIFS(Expenses!$D$2:$D$501,Expenses!$A$2:$A$501,">="&DATE(2026,9,1),Expenses!$A$2:$A$501,"<="&EOMONTH(DATE(2026,9,1),0)) | D10: =B10-C10
A11: Oct 2026 | B11: =SUMIFS(Sales!$E$2:$E$501,Sales!$A$2:$A$501,">="&DATE(2026,10,1),Sales!$A$2:$A$501,"<="&EOMONTH(DATE(2026,10,1),0)) | C11: =SUMIFS(Expenses!$D$2:$D$501,Expenses!$A$2:$A$501,">="&DATE(2026,10,1),Expenses!$A$2:$A$501,"<="&EOMONTH(DATE(2026,10,1),0)) | D11: =B11-C11
A12: Nov 2026 | B12: =SUMIFS(Sales!$E$2:$E$501,Sales!$A$2:$A$501,">="&DATE(2026,11,1),Sales!$A$2:$A$501,"<="&EOMONTH(DATE(2026,11,1),0)) | C12: =SUMIFS(Expenses!$D$2:$D$501,Expenses!$A$2:$A$501,">="&DATE(2026,11,1),Expenses!$A$2:$A$501,"<="&EOMONTH(DATE(2026,11,1),0)) | D12: =B12-C12
A13: Dec 2026 | B13: =SUMIFS(Sales!$E$2:$E$501,Sales!$A$2:$A$501,">="&DATE(2026,12,1),Sales!$A$2:$A$501,"<="&EOMONTH(DATE(2026,12,1),0)) | C13: =SUMIFS(Expenses!$D$2:$D$501,Expenses!$A$2:$A$501,">="&DATE(2026,12,1),Expenses!$A$2:$A$501,"<="&EOMONTH(DATE(2026,12,1),0)) | D13: =B13-C13

Sheet Buyer Guide
A1: BUYER GUIDE & SETUP INSTRUCTIONS
A2: 1. Save a copy of this workbook before editing.
A3: 2. Replace sample rows with your own records; do not overwrite header rows.
A4: 3. Enter sales, expenses, customers, products, invoices, tasks and service templates in their respective sheets.
A5: 4. Products sheet: Current Stock at or below Reorder Level indicates a low-stock item.
A6: 5. Monthly Summary uses the current calendar year and SUMIFS formulas. Adjust formula years if needed.
A7: 6. Profit is an operational estimate, not a tax or statutory accounting statement. Confirm GST/tax obligations with a qualified professional.
A8: 7. Required document lists are user-defined examples, not government-approved or legally complete checklists. Verify current official requirements for each service.
A9: 8. Protect customer privacy: collect only necessary data and store identity documents only when required, with appropriate safeguards.
A10: 9. Demo rows are examples only. Delete/replace them before real use.
A11: 10. Compatibility: Excel 2016+ or compatible spreadsheet software recommended for formulas and charts.
